transcribe_zh_en_p2/__init__.py
transcribe_zh_en_p2/main.py
transcribe_zh_en_p2-0.1.1.dist-info/METADATA
transcribe_zh_en_p2-0.1.1.dist-info/WHEEL
transcribe_zh_en_p2-0.1.1.dist-info/entry_points.txt
transcribe_zh_en_p2-0.1.1.dist-info/top_level.txt
transcribe_zh_en_p2-0.1.1.dist-info/RECORD
